[
  {
    "model": "users.user",
    "pk": 1,
    "fields": {
      "password": "pbkdf2_sha256$720000$YJST6ZL1sChNMJ5iQBpBmW$U8IPox9/KdRZxjb85FShOKEPeFc8YtcWtUcbzZJK+EE=",
      "last_login": "2024-04-28T14:23:15.073Z",
      "is_superuser": true,
      "first_name": "",
      "last_name": "",
      "is_staff": true,
      "is_active": true,
      "date_joined": "2024-04-14T14:37:35.569Z",
      "email": "admin@sky.pro",
      "phone_number": null,
      "avatar": "",
      "counter": null,
      "groups": [],
      "user_permissions": []
    }
  },
  {
    "model": "users.payment",
    "pk": 2,
    "fields": {
      "user": 1,
      "date_payment": "2024-04-28",
      "course": 1,
      "lesson": null,
      "amount": 15000,
      "payment_method": "cash"
    }
  },
  {
    "model": "users.payment",
    "pk": 3,
    "fields": {
      "user": 1,
      "date_payment": "2024-04-28",
      "course": null,
      "lesson": 7,
      "amount": 3000,
      "payment_method": "transfer to account"
    }
  },
  {
    "model": "users.payment",
    "pk": 4,
    "fields": {
      "user": 1,
      "date_payment": "2024-04-28",
      "course": null,
      "lesson": 8,
      "amount": 5000,
      "payment_method": "transfer to account"
    }
  }
]